fastapi_auth_user/__init__.py
fastapi_auth_user/__main__.py
fastapi_auth_user/auth/__init__.py
fastapi_auth_user/auth/exception.py
fastapi_auth_user/auth/permissions.py
fastapi_auth_user/auth/router.py
fastapi_auth_user/auth/service.py
fastapi_auth_user/auth/user_forms.py
fastapi_auth_user/config/__init__.py
fastapi_auth_user/config/setting.py
fastapi_auth_user/database/__init__.py
fastapi_auth_user/database/database.py
fastapi_auth_user/database/db_utils.py
fastapi_auth_user/database/exception.py
fastapi_auth_user/database/repository.py
fastapi_auth_user/models/__init__.py
fastapi_auth_user/models/enums.py
fastapi_auth_user/models/models.py
fastapi_auth_user/page/__init__.py
fastapi_auth_user/page/context.py
fastapi_auth_user/page/router.py
fastapi_auth_user/page/service.py
fastapi_auth_user/static/__init__.py
fastapi_auth_user/static/css/auth_panel.css
fastapi_auth_user/static/css/error_panel.css
fastapi_auth_user/static/css/user_panel.css
fastapi_auth_user/templates/__init__.py
fastapi_auth_user/templates/auth_panel.html
fastapi_auth_user/templates/error_panel.html
fastapi_auth_user/templates/user_panel.html
fastapi_auth_user/users/__init__.py
fastapi_auth_user/users/repository.py
fastapi_auth_user/users/router.py
fastapi_auth_user/users/schema.py
fastapi_auth_user/users/service.py
fastapi_auth_user-0.1.3.0.dist-info/entry_points.txt
fastapi_auth_user-0.1.3.0.dist-info/LICENSE
fastapi_auth_user-0.1.3.0.dist-info/METADATA
fastapi_auth_user-0.1.3.0.dist-info/WHEEL
fastapi_auth_user-0.1.3.0.dist-info/RECORD
