Metadata-Version: 2.1
Name: fastapi-auth-user
Version: 0.1.3.0
Summary: auth user
Author: Vittalius
Author-email: Vittalius@users.noreply.github.com
Requires-Python: >=3.11,<4.0
Classifier: Programming Language :: Python :: 3
Classifier: Programming Language :: Python :: 3.11
Requires-Dist: alembic (>=1.12.0,<2.0.0)
Requires-Dist: bcrypt (>=4.0.1,<5.0.0)
Requires-Dist: fastapi (>=0.95.0,<0.96.0)
Requires-Dist: jinja2 (>=3.1.2,<4.0.0)
Requires-Dist: passlib (>=1.7.4,<2.0.0)
Requires-Dist: psycopg2 (>=2.9.7,<3.0.0)
Requires-Dist: psycopg2-binary (>=2.9.7,<3.0.0)
Requires-Dist: pyjwt (>=2.6.0,<3.0.0)
Requires-Dist: python-decouple (>=3.8,<4.0)
Requires-Dist: python-dotenv (>=1.0.0,<2.0.0)
Requires-Dist: python-jose (>=3.3.0,<4.0.0)
Requires-Dist: python-multipart (>=0.0.6,<0.0.7)
Requires-Dist: sqlalchemy (>=2.0.8,<3.0.0)
Requires-Dist: uvicorn (>=0.21.1,<0.22.0)
